gtn_embed_sdk-1.0.2.dist-info/licenses/LICENSE
gtnapi/__init__.py
gtnapi/_auth.py
gtnapi/_connection.py
gtnapi/_requests.py
gtnapi/_shared.py
gtnapi/_streaming.py
gtn_embed_sdk-1.0.2.dist-info/METADATA
gtn_embed_sdk-1.0.2.dist-info/WHEEL
gtn_embed_sdk-1.0.2.dist-info/top_level.txt
gtn_embed_sdk-1.0.2.dist-info/RECORD
