Metadata-Version: 2.4
Name: gtn-embed-sdk
Version: 1.0.2
Summary: Python Software Developement Kit for GTN Fintech API
Author-email: Uditha Nagahawatta <n.uditha@gtngroup.com>
Maintainer-email: Fintech API Team <embed-pypi@gtngroup.com>
Project-URL: Homepage, https://github.com/GTN-Tech/python-sdk
Project-URL: Documentation, https://github.com/GTN-Tech/python-sdk
Project-URL: Source, https://github.com/GTN-Tech/python-sdk.git
Keywords: GTN API
Classifier: Development Status :: 5 - Production/Stable
Classifier: Programming Language :: Python :: 3.12
Classifier: Programming Language :: Python :: 3.13
Classifier: Operating System :: OS Independent
Classifier: Topic :: Internet
Classifier: Topic :: Software Development :: Libraries :: Python Modules
Classifier: Intended Audience :: Developers
Requires-Python: >=3.10
License-File: LICENSE
Requires-Dist: requests
Requires-Dist: cryptography
Requires-Dist: PyJWT
Requires-Dist: websocket-client
Requires-Dist: toml
Dynamic: license-file
